{
  "id": "V_kZo2Qot4Q",
  "title": "woman in red and white jacket beside man in gray crew neck t-shirt",
  "width": 6000,
  "height": 4000,
  "color": "#8c7359",
  "created_at": "2021-09-08T19:26:27Z",
  "updated_at": "2026-03-16T16:57:18Z",
  "likes": 17,
  "downloads": 1777,
  "views": 2544201,
  "attribution": {
    "photographer": {
      "name": "Alex Lujan",
      "username": "galuphotogtaphy",
      "portfolio_url": null,
      "bio": null,
      "location": "Boston, MA",
      "profile_image_url": "https://images.unsplash.com/profile-1631129223633-c8a42e3ecb69image?ixlib=rb-4.1.0&crop=faces&fit=crop&w=64&h=64"
    }
  },
  "urls": {
    "raw": "https://images.unsplash.com/photo-1631128869897-68e78bf4fb7e?ixid=M3wxMjA3fDB8MXxhbGx8fHx8fHx8fHwxNzczNjk3MjA3fA&ixlib=rb-4.1.0",
    "full": "https://images.unsplash.com/photo-1631128869897-68e78bf4fb7e?crop=entropy&cs=srgb&fm=jpg&ixid=M3wxMjA3fDB8MXxhbGx8fHx8fHx8fHwxNzczNjk3MjA3fA&ixlib=rb-4.1.0&q=85",
    "regular": "https://images.unsplash.com/photo-1631128869897-68e78bf4fb7e?crop=entropy&cs=tinysrgb&fit=max&fm=jpg&ixid=M3wxMjA3fDB8MXxhbGx8fHx8fHx8fHwxNzczNjk3MjA3fA&ixlib=rb-4.1.0&q=80&w=1080",
    "small": "https://images.unsplash.com/photo-1631128869897-68e78bf4fb7e?crop=entropy&cs=tinysrgb&fit=max&fm=jpg&ixid=M3wxMjA3fDB8MXxhbGx8fHx8fHx8fHwxNzczNjk3MjA3fA&ixlib=rb-4.1.0&q=80&w=400",
    "thumb": "https://images.unsplash.com/photo-1631128869897-68e78bf4fb7e?crop=entropy&cs=tinysrgb&fit=max&fm=jpg&ixid=M3wxMjA3fDB8MXxhbGx8fHx8fHx8fHwxNzczNjk3MjA3fA&ixlib=rb-4.1.0&q=80&w=200",
    "small_s3": "https://s3.us-west-2.amazonaws.com/images.unsplash.com/small/photo-1631128869897-68e78bf4fb7e"
  },
  "links": {
    "photographer_profile": "https://unsplash.com/@galuphotogtaphy",
    "download_unsplash": "https://unsplash.com/photos/woman-in-red-and-white-jacket-beside-man-in-gray-crew-neck-t-shirt-V_kZo2Qot4Q",
    "download_raw": null,
    "self": "https://api.unsplash.com/photos/woman-in-red-and-white-jacket-beside-man-in-gray-crew-neck-t-shirt-V_kZo2Qot4Q"
  },
  "usage_guidelines": {
    "free_to_use": "Yes, under the Unsplash License",
    "commercial_use": "Allowed",
    "requires_permission": "No",
    "requires_attribution": "Not required but appreciated",
    "unsplash_license_url": "https://unsplash.com/license"
  }
}